search_index-0.4.2.dist-info/METADATA
search_index-0.4.2.dist-info/WHEEL
search_index-0.4.2.dist-info/licenses/LICENSE
search_index/__init__.py
search_index/__init__.pyi
search_index/_internal.abi3.so
search_index/base.py
search_index/py.typed
search_index/similarity.py
search_index-0.4.2.dist-info/RECORD
