Metadata-Version: 2.4
Name: search-index
Version: 0.4.2
Classifier: Programming Language :: Rust
Classifier: Programming Language :: Python :: 3
Classifier: Topic :: Software Development :: Libraries
Classifier: Topic :: Text Processing
Classifier: Topic :: Utilities
Requires-Dist: sentence-transformers>=3.1
Requires-Dist: faiss>=1.11
Requires-Dist: sortedcontainers>=2.4.0
License-File: LICENSE
Summary: Search indices backed by Rust
Keywords: utilities,index,prefix,similarity,search
Author-email: Sebastian Walter <swalter@cs.uni-freiburg.de>
Requires-Python: >=3.12
Project-URL: Github, https://github.com/bastiscode/search-index
